kylo/__init__.py
kylo/auditor.py
kylo/cli.py
kylo/gemini_analyzer.py
kylo/readme_manager.py
kylo/secure_storage.py
kylo/security_scanner.py
kylo/usage_tracker.py
kylo/utils.py
kylo-1.0.0.dist-info/licenses/LICENSE
kylo-1.0.0.dist-info/METADATA
kylo-1.0.0.dist-info/WHEEL
kylo-1.0.0.dist-info/entry_points.txt
kylo-1.0.0.dist-info/top_level.txt
kylo-1.0.0.dist-info/RECORD
