Metadata-Version: 2.4
Name: kylo
Version: 1.0.0
Summary: AI-powered security code auditor and project alignment validator
Author-email: Leon Musk <alabimuiz0@gmail.com>
License: MIT
Project-URL: Homepage, https://kylo.pxxl.click
Project-URL: Documentation, https://kylo.pxxl.click
Project-URL: Repository, https://github.com/Shizzysagacious/kylo
Project-URL: Issues, https://github.com/Shizzysagacious/kylo/issues
Keywords: security,code-audit,vulnerability-scanner,static-analysis
Classifier: Development Status :: 4 - Beta
Classifier: Intended Audience :: Developers
Classifier: Programming Language :: Python :: 3
Classifier: Programming Language :: Python :: 3.8
Classifier: Programming Language :: Python :: 3.9
Classifier: Programming Language :: Python :: 3.10
Classifier: Programming Language :: Python :: 3.11
Classifier: Programming Language :: Python :: 3.12
Classifier: Topic :: Security
Classifier: Topic :: Software Development :: Quality Assurance
Requires-Python: >=3.8
License-File: LICENSE
Requires-Dist: click>=8.0
Requires-Dist: rich>=13.0.0
Requires-Dist: python-dotenv>=1.0.0
Requires-Dist: cryptography>=42.0.0
Requires-Dist: requests>=2.30.0
Provides-Extra: dev
Requires-Dist: pytest>=7.0.0; extra == "dev"
Requires-Dist: black>=23.0.0; extra == "dev"
Requires-Dist: mypy>=1.0.0; extra == "dev"
Dynamic: license-file
